pixelpop/__init__.py
pixelpop/_version.py
pixelpop/experimental/__init__.py
pixelpop/experimental/car.py
pixelpop/experimental/probabilistic.py
pixelpop/models/__init__.py
pixelpop/models/car.py
pixelpop/models/gwpop_models.py
pixelpop/models/probabilistic.py
pixelpop/result/__init__.py
pixelpop/result/save_popsummary.py
pixelpop/result/validate.py
pixelpop/utils/__init__.py
pixelpop/utils/data.py
pixelpop/utils/nearest_neighbor.py
pixelpop-0.2.3.dist-info/METADATA
pixelpop-0.2.3.dist-info/WHEEL
pixelpop-0.2.3.dist-info/top_level.txt
pixelpop-0.2.3.dist-info/RECORD
