Metadata-Version: 2.4
Name: pixelpop
Version: 0.2.3
Summary: Powered by numpyro and jax, package for fitting the GW population with a nonparametric binning scheme, where bins are correlated with only their nearest neighbors. Meant for inferring the GW population distribution nonparametrically in higher dimensions.
Author-email: Jack Heinzel <heinzelj@mit.edu>
License: MIT
Project-URL: homepage, https://git.ligo.org/jack.heinzel/pixelpop
Requires-Python: >=3.11
Requires-Dist: numpy
Requires-Dist: scipy
Requires-Dist: jax
Requires-Dist: pandas
Requires-Dist: numpyro
Requires-Dist: gwpopulation
Requires-Dist: gwpopulation_pipe
Requires-Dist: wcosmo
Requires-Dist: astropy
Requires-Dist: h5ify
Requires-Dist: popsummary
Requires-Dist: arviz
Requires-Dist: population_error
Requires-Dist: xarray
Requires-Dist: unxt
